GZQmy_package/__init__.py
GZQmy_package/module1.py
gzqmy_package-0.1.dist-info/LICENSE
gzqmy_package-0.1.dist-info/WHEEL
gzqmy_package-0.1.dist-info/METADATA
gzqmy_package-0.1.dist-info/RECORD
