Metadata-Version: 2.3
Name: GZQmy_package
Version: 0.1
Summary: This is the GZQmy_package package.
Author-email: Zq_G <1653119108@qq.com>
Classifier: License :: OSI Approved :: MIT License
Project-URL: Home, https://www.bing.com/search?q=flit%E7%AE%A1%E7%90%86python&form=ANNTH1&refig=676a9b293c9242a69be184491edbcdf5&pc=CNNDDB
